README
setup.py
EggsHelper.egg-info/PKG-INFO
EggsHelper.egg-info/SOURCES.txt
EggsHelper.egg-info/dependency_links.txt
EggsHelper.egg-info/requires.txt
EggsHelper.egg-info/top_level.txt
eggshelper/__init__.py
eggshelper/run_me.py
