Metadata-Version: 1.0
Name: EggsHelper
Version: 1.0.0
Summary: Sample 'eggified' application anyone can use as a skeleton.
Home-page: http://seberino.org/
Author: Christian Seberino
Author-email: chris@seberino.org
License: GPL
Platform: UNKNOWN
